{
  "version" : "1.2.0",
  "resources" : {
    "RoleWeight" : {
      "name" : "RoleWeight.json",
      "filePath" : "assets/data/zh_CN/RoleWeight.json",
      "aimPath" : "assets/data/zh_CN/RoleWeight.json",
      "md5" : "373bc562bf4ce69245424ed3692602b0"
    },
    "BaseData" : {
      "name" : "BaseData.json",
      "filePath" : "assets/data/default/BaseData.json",
      "aimPath" : "assets/data/default/BaseData.json",
      "md5" : "48d8a303c5e886ced7d311b0d467f69c"
    },
    "RoleHeader" : {
      "name" : "RoleHeader.json",
      "filePath" : "assets/data/default/RoleHeader.json",
      "aimPath" : "assets/data/default/RoleHeader.json",
      "md5" : "2b44253e23d823528306d7835b8bd696"
    }
  }
}